{"frames":{"player1":{"frame":{"x":0,"y":0,"w":128,"h":128},"rotated":false,"trimmed":false,"spriteSourceSize":{"x":0,"y":0,"w":128,"h":128},"sourceSize":{"w":128,"h":128}},"player2":{"frame":{"x":0,"y":129,"w":128,"h":128},"rotated":false,"trimmed":false,"spriteSourceSize":{"x":0,"y":0,"w":128,"h":128},"sourceSize":{"w":128,"h":128}},"player3":{"frame":{"x":129,"y":0,"w":128,"h":128},"rotated":false,"trimmed":false,"spriteSourceSize":{"x":0,"y":0,"w":128,"h":128},"sourceSize":{"w":128,"h":128}},"player4":{"frame":{"x":129,"y":129,"w":128,"h":128},"rotated":false,"trimmed":false,"spriteSourceSize":{"x":0,"y":0,"w":128,"h":128},"sourceSize":{"w":128,"h":128}},"player5":{"frame":{"x":0,"y":258,"w":128,"h":128},"rotated":false,"trimmed":false,"spriteSourceSize":{"x":0,"y":0,"w":128,"h":128},"sourceSize":{"w":128,"h":128}},"player6":{"frame":{"x":129,"y":258,"w":128,"h":128},"rotated":false,"trimmed":false,"spriteSourceSize":{"x":0,"y":0,"w":128,"h":128},"sourceSize":{"w":128,"h":128}},"player7":{"frame":{"x":258,"y":0,"w":128,"h":128},"rotated":false,"trimmed":false,"spriteSourceSize":{"x":0,"y":0,"w":128,"h":128},"sourceSize":{"w":128,"h":128}},"player8":{"frame":{"x":258,"y":129,"w":128,"h":128},"rotated":false,"trimmed":false,"spriteSourceSize":{"x":0,"y":0,"w":128,"h":128},"sourceSize":{"w":128,"h":128}},"player9":{"frame":{"x":258,"y":258,"w":128,"h":128},"rotated":false,"trimmed":false,"spriteSourceSize":{"x":0,"y":0,"w":128,"h":128},"sourceSize":{"w":128,"h":128}},"player10":{"frame":{"x":0,"y":387,"w":128,"h":128},"rotated":false,"trimmed":false,"spriteSourceSize":{"x":0,"y":0,"w":128,"h":128},"sourceSize":{"w":128,"h":128}},"player11":{"frame":{"x":129,"y":387,"w":128,"h":128},"rotated":false,"trimmed":false,"spriteSourceSize":{"x":0,"y":0,"w":128,"h":128},"sourceSize":{"w":128,"h":128}},"player12":{"frame":{"x":258,"y":387,"w":128,"h":128},"rotated":false,"trimmed":false,"spriteSourceSize":{"x":0,"y":0,"w":128,"h":128},"sourceSize":{"w":128,"h":128}},"player13":{"frame":{"x":387,"y":0,"w":128,"h":128},"rotated":false,"trimmed":false,"spriteSourceSize":{"x":0,"y":0,"w":128,"h":128},"sourceSize":{"w":128,"h":128}}},"meta":{"app":"https://www.leshylabs.com/apps/sstool/","version":"Leshy SpriteSheet Tool v0.8.4","image":"spritesheet.png","size":{"w":515,"h":515},"scale":1}}