{"frames":{"vfx_down2":{"frame":{"x":0,"y":0,"w":128,"h":128},"rotated":false,"trimmed":false,"spriteSourceSize":{"x":0,"y":0,"w":128,"h":128},"sourceSize":{"w":128,"h":128}},"vfx_down3":{"frame":{"x":0,"y":129,"w":128,"h":128},"rotated":false,"trimmed":false,"spriteSourceSize":{"x":0,"y":0,"w":128,"h":128},"sourceSize":{"w":128,"h":128}},"vfx_down4":{"frame":{"x":129,"y":0,"w":128,"h":128},"rotated":false,"trimmed":false,"spriteSourceSize":{"x":0,"y":0,"w":128,"h":128},"sourceSize":{"w":128,"h":128}},"vfx_down5":{"frame":{"x":129,"y":129,"w":128,"h":128},"rotated":false,"trimmed":false,"spriteSourceSize":{"x":0,"y":0,"w":128,"h":128},"sourceSize":{"w":128,"h":128}},"vfx_down6":{"frame":{"x":0,"y":258,"w":128,"h":128},"rotated":false,"trimmed":false,"spriteSourceSize":{"x":0,"y":0,"w":128,"h":128},"sourceSize":{"w":128,"h":128}},"vfx_up1":{"frame":{"x":129,"y":258,"w":128,"h":128},"rotated":false,"trimmed":false,"spriteSourceSize":{"x":0,"y":0,"w":128,"h":128},"sourceSize":{"w":128,"h":128}},"vfx_up2":{"frame":{"x":258,"y":0,"w":128,"h":128},"rotated":false,"trimmed":false,"spriteSourceSize":{"x":0,"y":0,"w":128,"h":128},"sourceSize":{"w":128,"h":128}},"vfx_up3":{"frame":{"x":258,"y":129,"w":128,"h":128},"rotated":false,"trimmed":false,"spriteSourceSize":{"x":0,"y":0,"w":128,"h":128},"sourceSize":{"w":128,"h":128}},"vfx_up4":{"frame":{"x":258,"y":258,"w":128,"h":128},"rotated":false,"trimmed":false,"spriteSourceSize":{"x":0,"y":0,"w":128,"h":128},"sourceSize":{"w":128,"h":128}},"vfx_up5":{"frame":{"x":0,"y":387,"w":128,"h":128},"rotated":false,"trimmed":false,"spriteSourceSize":{"x":0,"y":0,"w":128,"h":128},"sourceSize":{"w":128,"h":128}},"vfx_up6":{"frame":{"x":129,"y":387,"w":128,"h":128},"rotated":false,"trimmed":false,"spriteSourceSize":{"x":0,"y":0,"w":128,"h":128},"sourceSize":{"w":128,"h":128}},"vfx_down1":{"frame":{"x":258,"y":387,"w":128,"h":128},"rotated":false,"trimmed":false,"spriteSourceSize":{"x":0,"y":0,"w":128,"h":128},"sourceSize":{"w":128,"h":128}}},"meta":{"app":"https://www.leshylabs.com/apps/sstool/","version":"Leshy SpriteSheet Tool v0.8.4","image":"vfx_spritesheet.png","size":{"w":386,"h":515},"scale":1}}